{
  "annotations": {
    "list": [
      {
        "builtIn": 1,
        "datasource": {
          "type": "grafana",
          "uid": "-- Grafana --"
        },
        "enable": true,
        "hide": true,
        "iconColor": "rgba(0, 211, 255, 1)",
        "name": "Annotations & Alerts",
        "type": "dashboard"
      }
    ]
  },
  "editable": true,
  "fiscalYearStartMonth": 0,
  "graphTooltip": 1,
  "id": 3,
  "links": [],
  "panels": [
    {
      "collapsed": false,
      "gridPos": {
        "h": 1,
        "w": 24,
        "x": 0,
        "y": 0
      },
      "id": 100,
      "panels": [],
      "title": "Overview",
      "type": "row"
    },
    {
      "datasource": {
        "type": "grafana-clickhouse-datasource",
        "uid": "${DS_CLICKHOUSE}"
      },
      "fieldConfig": {
        "defaults": {
          "color": {
            "mode": "thresholds"
          },
          "mappings": [],
          "thresholds": {
            "mode": "absolute",
            "steps": [
              {
                "color": "green",
                "value": 0
              }
            ]
          },
          "unit": "short"
        },
        "overrides": []
      },
      "gridPos": {
        "h": 4,
        "w": 3,
        "x": 0,
        "y": 1
      },
      "id": 1,
      "options": {
        "colorMode": "value",
        "graphMode": "area",
        "justifyMode": "auto",
        "orientation": "auto",
        "percentChangeColorMode": "standard",
        "reduceOptions": {
          "calcs": [
            "lastNotNull"
          ],
          "fields": "",
          "values": false
        },
        "showPercentChange": false,
        "textMode": "auto",
        "wideLayout": true
      },
      "pluginVersion": "12.3.1",
      "targets": [
        {
          "editorType": "sql",
          "format": 1,
          "queryType": "table",
          "rawSql": "SELECT count(*) AS total FROM logs_nginx_${deployment_env}.access WHERE $__timeFilter(timestamp) AND host LIKE '$host' AND toString(status) LIKE '$status' AND method LIKE '$method' AND country_code LIKE '$country'",
          "refId": "A"
        }
      ],
      "title": "Total Requests",
      "type": "stat"
    },
    {
      "datasource": {
        "type": "grafana-clickhouse-datasource",
        "uid": "${DS_CLICKHOUSE}"
      },
      "fieldConfig": {
        "defaults": {
          "color": {
            "mode": "thresholds"
          },
          "decimals": 1,
          "mappings": [],
          "thresholds": {
            "mode": "absolute",
            "steps": [
              {
                "color": "green",
                "value": 0
              }
            ]
          },
          "unit": "reqps"
        },
        "overrides": []
      },
      "gridPos": {
        "h": 4,
        "w": 3,
        "x": 3,
        "y": 1
      },
      "id": 2,
      "options": {
        "colorMode": "value",
        "graphMode": "area",
        "justifyMode": "auto",
        "orientation": "auto",
        "percentChangeColorMode": "standard",
        "reduceOptions": {
          "calcs": [
            "lastNotNull"
          ],
          "fields": "",
          "values": false
        },
        "showPercentChange": false,
        "textMode": "auto",
        "wideLayout": true
      },
      "pluginVersion": "12.3.1",
      "targets": [
        {
          "editorType": "sql",
          "format": 1,
          "queryType": "table",
          "rawSql": "SELECT if(count() = 0, 0, round(count() / greatest(dateDiff('second', min(timestamp), max(timestamp)), 1), 2)) AS rps FROM logs_nginx_${deployment_env}.access WHERE $__timeFilter(timestamp) AND host LIKE '$host' AND toString(status) LIKE '$status' AND method LIKE '$method' AND country_code LIKE '$country'",
          "refId": "A"
        }
      ],
      "title": "RPS",
      "type": "stat"
    },
    {
      "datasource": {
        "type": "grafana-clickhouse-datasource",
        "uid": "${DS_CLICKHOUSE}"
      },
      "fieldConfig": {
        "defaults": {
          "color": {
            "mode": "thresholds"
          },
          "mappings": [],
          "thresholds": {
            "mode": "absolute",
            "steps": [
              {
                "color": "blue",
                "value": 0
              }
            ]
          },
          "unit": "short"
        },
        "overrides": []
      },
      "gridPos": {
        "h": 4,
        "w": 3,
        "x": 6,
        "y": 1
      },
      "id": 3,
      "options": {
        "colorMode": "value",
        "graphMode": "area",
        "justifyMode": "auto",
        "orientation": "auto",
        "percentChangeColorMode": "standard",
        "reduceOptions": {
          "calcs": [
            "lastNotNull"
          ],
          "fields": "",
          "values": false
        },
        "showPercentChange": false,
        "textMode": "auto",
        "wideLayout": true
      },
      "pluginVersion": "12.3.1",
      "targets": [
        {
          "editorType": "sql",
          "format": 1,
          "queryType": "table",
          "rawSql": "SELECT uniqExact(remote_addr) AS unique_ips FROM logs_nginx_${deployment_env}.access WHERE $__timeFilter(timestamp) AND host LIKE '$host' AND toString(status) LIKE '$status' AND method LIKE '$method' AND country_code LIKE '$country'",
          "refId": "A"
        }
      ],
      "title": "Unique IPs",
      "type": "stat"
    },
    {
      "datasource": {
        "type": "grafana-clickhouse-datasource",
        "uid": "${DS_CLICKHOUSE}"
      },
      "fieldConfig": {
        "defaults": {
          "color": {
            "mode": "thresholds"
          },
          "mappings": [],
          "max": 100,
          "min": 0,
          "thresholds": {
            "mode": "absolute",
            "steps": [
              {
                "color": "green",
                "value": 0
              },
              {
                "color": "yellow",
                "value": 1
              },
              {
                "color": "red",
                "value": 5
              }
            ]
          },
          "unit": "percent"
        },
        "overrides": []
      },
      "gridPos": {
        "h": 4,
        "w": 3,
        "x": 9,
        "y": 1
      },
      "id": 4,
      "options": {
        "colorMode": "value",
        "graphMode": "area",
        "justifyMode": "auto",
        "orientation": "auto",
        "percentChangeColorMode": "standard",
        "reduceOptions": {
          "calcs": [
            "lastNotNull"
          ],
          "fields": "",
          "values": false
        },
        "showPercentChange": false,
        "textMode": "auto",
        "wideLayout": true
      },
      "pluginVersion": "12.3.1",
      "targets": [
        {
          "editorType": "sql",
          "format": 1,
          "queryType": "table",
          "rawSql": "SELECT round(countIf(status >= 400 AND status != 444) * 100.0 / count(), 2) AS error_rate FROM logs_nginx_${deployment_env}.access WHERE $__timeFilter(timestamp) AND host LIKE '$host' AND toString(status) LIKE '$status' AND method LIKE '$method' AND country_code LIKE '$country'",
          "refId": "A"
        }
      ],
      "title": "Error Rate",
      "type": "stat"
    },
    {
      "datasource": {
        "type": "grafana-clickhouse-datasource",
        "uid": "${DS_CLICKHOUSE}"
      },
      "fieldConfig": {
        "defaults": {
          "color": {
            "mode": "thresholds"
          },
          "mappings": [],
          "thresholds": {
            "mode": "absolute",
            "steps": [
              {
                "color": "green",
                "value": 0
              },
              {
                "color": "yellow",
                "value": 500
              },
              {
                "color": "red",
                "value": 1000
              }
            ]
          },
          "unit": "ms"
        },
        "overrides": []
      },
      "gridPos": {
        "h": 4,
        "w": 3,
        "x": 12,
        "y": 1
      },
      "id": 5,
      "options": {
        "colorMode": "value",
        "graphMode": "area",
        "justifyMode": "auto",
        "orientation": "auto",
        "percentChangeColorMode": "standard",
        "reduceOptions": {
          "calcs": [
            "lastNotNull"
          ],
          "fields": "",
          "values": false
        },
        "showPercentChange": false,
        "textMode": "auto",
        "wideLayout": true
      },
      "pluginVersion": "12.3.1",
      "targets": [
        {
          "editorType": "sql",
          "format": 1,
          "queryType": "table",
          "rawSql": "SELECT round(quantile(0.95)(request_time) * 1000, 2) AS p95_ms FROM logs_nginx_${deployment_env}.access WHERE $__timeFilter(timestamp) AND request_time > 0 AND host LIKE '$host' AND toString(status) LIKE '$status' AND method LIKE '$method' AND country_code LIKE '$country'",
          "refId": "A"
        }
      ],
      "title": "Response Time (P95)",
      "type": "stat"
    },
    {
      "datasource": {
        "type": "grafana-clickhouse-datasource",
        "uid": "${DS_CLICKHOUSE}"
      },
      "fieldConfig": {
        "defaults": {
          "color": {
            "mode": "thresholds"
          },
          "decimals": 1,
          "mappings": [],
          "max": 100,
          "min": 0,
          "thresholds": {
            "mode": "absolute",
            "steps": [
              {
                "color": "red",
                "value": 0
              },
              {
                "color": "yellow",
                "value": 50
              },
              {
                "color": "green",
                "value": 80
              }
            ]
          },
          "unit": "percent"
        },
        "overrides": []
      },
      "gridPos": {
        "h": 4,
        "w": 3,
        "x": 15,
        "y": 1
      },
      "id": 6,
      "options": {
        "colorMode": "value",
        "graphMode": "area",
        "justifyMode": "auto",
        "orientation": "auto",
        "percentChangeColorMode": "standard",
        "reduceOptions": {
          "calcs": [
            "lastNotNull"
          ],
          "fields": "",
          "values": false
        },
        "showPercentChange": false,
        "textMode": "auto",
        "wideLayout": true
      },
      "pluginVersion": "12.3.1",
      "targets": [
        {
          "editorType": "sql",
          "format": 1,
          "queryType": "table",
          "rawSql": "SELECT if(countIf(upstream_cache_status != '') = 0, 0, round(countIf(upstream_cache_status = 'HIT') * 100.0 / countIf(upstream_cache_status != ''), 2)) AS cache_hit_pct FROM logs_nginx_${deployment_env}.access WHERE $__timeFilter(timestamp) AND host LIKE '$host' AND toString(status) LIKE '$status' AND method LIKE '$method' AND country_code LIKE '$country'",
          "refId": "A"
        }
      ],
      "title": "Cache Hit %",
      "type": "stat"
    },
    {
      "datasource": {
        "type": "grafana-clickhouse-datasource",
        "uid": "${DS_CLICKHOUSE}"
      },
      "fieldConfig": {
        "defaults": {
          "color": {
            "mode": "thresholds"
          },
          "mappings": [],
          "thresholds": {
            "mode": "absolute",
            "steps": [
              {
                "color": "purple",
                "value": 0
              }
            ]
          },
          "unit": "decbytes"
        },
        "overrides": []
      },
      "gridPos": {
        "h": 4,
        "w": 3,
        "x": 18,
        "y": 1
      },
      "id": 7,
      "options": {
        "colorMode": "value",
        "graphMode": "area",
        "justifyMode": "auto",
        "orientation": "auto",
        "percentChangeColorMode": "standard",
        "reduceOptions": {
          "calcs": [
            "lastNotNull"
          ],
          "fields": "",
          "values": false
        },
        "showPercentChange": false,
        "textMode": "auto",
        "wideLayout": true
      },
      "pluginVersion": "12.3.1",
      "targets": [
        {
          "editorType": "sql",
          "format": 1,
          "queryType": "table",
          "rawSql": "SELECT sum(bytes_sent) AS bandwidth FROM logs_nginx_${deployment_env}.access WHERE $__timeFilter(timestamp) AND host LIKE '$host' AND toString(status) LIKE '$status' AND method LIKE '$method' AND country_code LIKE '$country'",
          "refId": "A"
        }
      ],
      "title": "Bandwidth",
      "type": "stat"
    },
    {
      "datasource": {
        "type": "grafana-clickhouse-datasource",
        "uid": "${DS_CLICKHOUSE}"
      },
      "fieldConfig": {
        "defaults": {
          "color": {
            "mode": "thresholds"
          },
          "mappings": [],
          "max": 100,
          "min": 0,
          "thresholds": {
            "mode": "absolute",
            "steps": [
              {
                "color": "orange",
                "value": 0
              },
              {
                "color": "green",
                "value": 90
              }
            ]
          },
          "unit": "percent"
        },
        "overrides": []
      },
      "gridPos": {
        "h": 4,
        "w": 3,
        "x": 21,
        "y": 1
      },
      "id": 8,
      "options": {
        "colorMode": "value",
        "graphMode": "area",
        "justifyMode": "auto",
        "orientation": "auto",
        "percentChangeColorMode": "standard",
        "reduceOptions": {
          "calcs": [
            "lastNotNull"
          ],
          "fields": "",
          "values": false
        },
        "showPercentChange": false,
        "textMode": "auto",
        "wideLayout": true
      },
      "pluginVersion": "12.3.1",
      "targets": [
        {
          "editorType": "sql",
          "format": 1,
          "queryType": "table",
          "rawSql": "SELECT round(countIf(cf_ray != '') * 100.0 / count(), 2) AS cf_pct FROM logs_nginx_${deployment_env}.access WHERE $__timeFilter(timestamp) AND host LIKE '$host' AND toString(status) LIKE '$status' AND method LIKE '$method' AND country_code LIKE '$country'",
          "refId": "A"
        }
      ],
      "title": "CDN Coverage",
      "type": "stat"
    },
    {
      "collapsed": false,
      "gridPos": {
        "h": 1,
        "w": 24,
        "x": 0,
        "y": 5
      },
      "id": 101,
      "panels": [],
      "title": "Traffic",
      "type": "row"
    },
    {
      "datasource": {
        "type": "grafana-clickhouse-datasource",
        "uid": "${DS_CLICKHOUSE}"
      },
      "fieldConfig": {
        "defaults": {
          "color": {
            "mode": "palette-classic"
          },
          "custom": {
            "axisBorderShow": false,
            "axisCenteredZero": false,
            "axisColorMode": "text",
            "axisLabel": "",
            "axisPlacement": "auto",
            "barAlignment": 0,
            "barWidthFactor": 0.6,
            "drawStyle": "line",
            "fillOpacity": 10,
            "gradientMode": "opacity",
            "hideFrom": {
              "legend": false,
              "tooltip": false,
              "viz": false
            },
            "insertNulls": false,
            "lineInterpolation": "smooth",
            "lineWidth": 1,
            "pointSize": 5,
            "scaleDistribution": {
              "type": "linear"
            },
            "showPoints": "never",
            "showValues": false,
            "spanNulls": false,
            "stacking": {
              "group": "A",
              "mode": "none"
            },
            "thresholdsStyle": {
              "mode": "off"
            }
          },
          "mappings": [],
          "thresholds": {
            "mode": "absolute",
            "steps": [
              {
                "color": "green",
                "value": 0
              }
            ]
          }
        },
        "overrides": []
      },
      "gridPos": {
        "h": 8,
        "w": 16,
        "x": 0,
        "y": 6
      },
      "id": 10,
      "options": {
        "legend": {
          "calcs": [
            "mean",
            "max"
          ],
          "displayMode": "list",
          "placement": "bottom",
          "showLegend": true
        },
        "tooltip": {
          "hideZeros": false,
          "mode": "multi",
          "sort": "desc"
        }
      },
      "pluginVersion": "12.3.1",
      "targets": [
        {
          "editorType": "sql",
          "format": 1,
          "queryType": "table",
          "rawSql": "SELECT $__timeInterval(timestamp) AS time, count() AS requests FROM logs_nginx_${deployment_env}.access WHERE $__timeFilter(timestamp) AND host LIKE '$host' AND toString(status) LIKE '$status' AND method LIKE '$method' AND country_code LIKE '$country' GROUP BY time ORDER BY time",
          "refId": "A"
        }
      ],
      "title": "Requests Over Time",
      "type": "timeseries"
    },
    {
      "datasource": {
        "type": "grafana-clickhouse-datasource",
        "uid": "${DS_CLICKHOUSE}"
      },
      "fieldConfig": {
        "defaults": {
          "color": {
            "mode": "thresholds"
          },
          "custom": {
            "align": "auto",
            "cellOptions": {
              "type": "auto"
            },
            "footer": {
              "reducers": []
            },
            "inspect": false
          },
          "mappings": [],
          "thresholds": {
            "mode": "absolute",
            "steps": [
              {
                "color": "green",
                "value": 0
              }
            ]
          }
        },
        "overrides": [
          {
            "matcher": {
              "id": "byName",
              "options": "requests"
            },
            "properties": [
              {
                "id": "custom.cellOptions",
                "value": {
                  "mode": "gradient",
                  "type": "gauge",
                  "valueDisplayMode": "text"
                }
              }
            ]
          },
          {
            "matcher": {
              "id": "byName",
              "options": "p95_ms"
            },
            "properties": [
              {
                "id": "unit",
                "value": "ms"
              },
              {
                "id": "thresholds",
                "value": {
                  "mode": "absolute",
                  "steps": [
                    {
                      "color": "green",
                      "value": 0
                    },
                    {
                      "color": "yellow",
                      "value": 500
                    },
                    {
                      "color": "red",
                      "value": 1000
                    }
                  ]
                }
              },
              {
                "id": "custom.cellOptions",
                "value": {
                  "mode": "basic",
                  "type": "color-background"
                }
              }
            ]
          },
          {
            "matcher": {
              "id": "byName",
              "options": "errors_5xx"
            },
            "properties": [
              {
                "id": "thresholds",
                "value": {
                  "mode": "absolute",
                  "steps": [
                    {
                      "color": "green",
                      "value": 0
                    },
                    {
                      "color": "red",
                      "value": 1
                    }
                  ]
                }
              },
              {
                "id": "custom.cellOptions",
                "value": {
                  "mode": "basic",
                  "type": "color-background"
                }
              }
            ]
          }
        ]
      },
      "gridPos": {
        "h": 8,
        "w": 8,
        "x": 16,
        "y": 6
      },
      "id": 11,
      "options": {
        "cellHeight": "sm",
        "showHeader": true,
        "sortBy": [
          {
            "desc": true,
            "displayName": "requests"
          }
        ]
      },
      "pluginVersion": "12.3.1",
      "targets": [
        {
          "editorType": "sql",
          "format": 1,
          "queryType": "table",
          "rawSql": "SELECT host, count() AS requests, round(quantile(0.95)(request_time) * 1000, 0) AS p95_ms, countIf(status >= 500) AS errors_5xx FROM logs_nginx_${deployment_env}.access WHERE $__timeFilter(timestamp) GROUP BY host ORDER BY requests DESC LIMIT 10",
          "refId": "A"
        }
      ],
      "title": "Traffic by Host",
      "type": "table"
    },
    {
      "collapsed": false,
      "gridPos": {
        "h": 1,
        "w": 24,
        "x": 0,
        "y": 14
      },
      "id": 102,
      "panels": [],
      "title": "Performance",
      "type": "row"
    },
    {
      "datasource": {
        "type": "grafana-clickhouse-datasource",
        "uid": "${DS_CLICKHOUSE}"
      },
      "fieldConfig": {
        "defaults": {
          "color": {
            "mode": "palette-classic"
          },
          "custom": {
            "axisBorderShow": false,
            "axisCenteredZero": false,
            "axisColorMode": "text",
            "axisLabel": "",
            "axisPlacement": "auto",
            "barAlignment": 0,
            "barWidthFactor": 0.6,
            "drawStyle": "line",
            "fillOpacity": 0,
            "gradientMode": "none",
            "hideFrom": {
              "legend": false,
              "tooltip": false,
              "viz": false
            },
            "insertNulls": false,
            "lineInterpolation": "linear",
            "lineWidth": 1,
            "pointSize": 5,
            "scaleDistribution": {
              "type": "linear"
            },
            "showPoints": "never",
            "showValues": false,
            "spanNulls": false,
            "stacking": {
              "group": "A",
              "mode": "none"
            },
            "thresholdsStyle": {
              "mode": "off"
            }
          },
          "mappings": [],
          "thresholds": {
            "mode": "absolute",
            "steps": [
              {
                "color": "green",
                "value": 0
              }
            ]
          },
          "unit": "ms"
        },
        "overrides": []
      },
      "gridPos": {
        "h": 8,
        "w": 12,
        "x": 0,
        "y": 15
      },
      "id": 12,
      "options": {
        "legend": {
          "calcs": [
            "mean",
            "max"
          ],
          "displayMode": "list",
          "placement": "bottom",
          "showLegend": true
        },
        "tooltip": {
          "hideZeros": false,
          "mode": "multi",
          "sort": "desc"
        }
      },
      "pluginVersion": "12.3.1",
      "targets": [
        {
          "editorType": "sql",
          "format": 1,
          "queryType": "table",
          "rawSql": "SELECT $__timeInterval(timestamp) AS time, round(quantile(0.5)(request_time) * 1000, 2) AS p50, round(quantile(0.95)(request_time) * 1000, 2) AS p95, round(quantile(0.99)(request_time) * 1000, 2) AS p99 FROM logs_nginx_${deployment_env}.access WHERE $__timeFilter(timestamp) AND request_time > 0 AND host LIKE '$host' AND toString(status) LIKE '$status' AND method LIKE '$method' AND country_code LIKE '$country' GROUP BY time ORDER BY time",
          "refId": "A"
        }
      ],
      "title": "Latency Percentiles",
      "type": "timeseries"
    },
    {
      "datasource": {
        "type": "grafana-clickhouse-datasource",
        "uid": "${DS_CLICKHOUSE}"
      },
      "fieldConfig": {
        "defaults": {
          "color": {
            "mode": "palette-classic"
          },
          "custom": {
            "axisBorderShow": false,
            "axisCenteredZero": false,
            "axisColorMode": "text",
            "axisLabel": "",
            "axisPlacement": "auto",
            "barAlignment": 0,
            "barWidthFactor": 0.6,
            "drawStyle": "line",
            "fillOpacity": 10,
            "gradientMode": "opacity",
            "hideFrom": {
              "legend": false,
              "tooltip": false,
              "viz": false
            },
            "insertNulls": false,
            "lineInterpolation": "linear",
            "lineWidth": 1,
            "pointSize": 5,
            "scaleDistribution": {
              "type": "linear"
            },
            "showPoints": "never",
            "showValues": false,
            "spanNulls": false,
            "stacking": {
              "group": "A",
              "mode": "none"
            },
            "thresholdsStyle": {
              "mode": "off"
            }
          },
          "mappings": [],
          "thresholds": {
            "mode": "absolute",
            "steps": [
              {
                "color": "green",
                "value": 0
              }
            ]
          },
          "unit": "ms"
        },
        "overrides": [
          {
            "matcher": {
              "id": "byName",
              "options": "backend_p95"
            },
            "properties": [
              {
                "id": "color",
                "value": {
                  "fixedColor": "orange",
                  "mode": "fixed"
                }
              }
            ]
          },
          {
            "matcher": {
              "id": "byName",
              "options": "nginx_overhead_p95"
            },
            "properties": [
              {
                "id": "color",
                "value": {
                  "fixedColor": "blue",
                  "mode": "fixed"
                }
              }
            ]
          }
        ]
      },
      "gridPos": {
        "h": 8,
        "w": 12,
        "x": 12,
        "y": 15
      },
      "id": 13,
      "options": {
        "legend": {
          "calcs": [
            "mean",
            "max"
          ],
          "displayMode": "list",
          "placement": "bottom",
          "showLegend": true
        },
        "tooltip": {
          "hideZeros": false,
          "mode": "multi",
          "sort": "desc"
        }
      },
      "pluginVersion": "12.3.1",
      "targets": [
        {
          "editorType": "sql",
          "format": 1,
          "queryType": "table",
          "rawSql": "SELECT $__timeInterval(timestamp) AS time, round(quantile(0.95)(upstream_response_time) * 1000, 2) AS backend_p95, round(quantile(0.95)(request_time - upstream_response_time) * 1000, 2) AS nginx_overhead_p95 FROM logs_nginx_${deployment_env}.access WHERE $__timeFilter(timestamp) AND upstream_response_time > 0 AND host LIKE '$host' AND toString(status) LIKE '$status' AND method LIKE '$method' AND country_code LIKE '$country' GROUP BY time ORDER BY time",
          "refId": "A"
        }
      ],
      "title": "Backend vs NGINX Overhead (P95)",
      "type": "timeseries"
    },
    {
      "collapsed": false,
      "gridPos": {
        "h": 1,
        "w": 24,
        "x": 0,
        "y": 23
      },
      "id": 103,
      "panels": [],
      "title": "Endpoints",
      "type": "row"
    },
    {
      "datasource": {
        "type": "grafana-clickhouse-datasource",
        "uid": "${DS_CLICKHOUSE}"
      },
      "fieldConfig": {
        "defaults": {
          "color": {
            "mode": "thresholds"
          },
          "custom": {
            "align": "auto",
            "cellOptions": {
              "type": "auto"
            },
            "footer": {
              "reducers": []
            },
            "inspect": false
          },
          "mappings": [],
          "thresholds": {
            "mode": "absolute",
            "steps": [
              {
                "color": "green",
                "value": 0
              }
            ]
          }
        },
        "overrides": [
          {
            "matcher": {
              "id": "byName",
              "options": "requests"
            },
            "properties": [
              {
                "id": "custom.cellOptions",
                "value": {
                  "mode": "gradient",
                  "type": "gauge",
                  "valueDisplayMode": "text"
                }
              }
            ]
          },
          {
            "matcher": {
              "id": "byName",
              "options": "avg_ms"
            },
            "properties": [
              {
                "id": "unit",
                "value": "ms"
              }
            ]
          },
          {
            "matcher": {
              "id": "byName",
              "options": "p95_ms"
            },
            "properties": [
              {
                "id": "unit",
                "value": "ms"
              },
              {
                "id": "thresholds",
                "value": {
                  "mode": "absolute",
                  "steps": [
                    {
                      "color": "green",
                      "value": 0
                    },
                    {
                      "color": "yellow",
                      "value": 500
                    },
                    {
                      "color": "red",
                      "value": 1000
                    }
                  ]
                }
              },
              {
                "id": "custom.cellOptions",
                "value": {
                  "mode": "basic",
                  "type": "color-background"
                }
              }
            ]
          },
          {
            "matcher": {
              "id": "byName",
              "options": "errors"
            },
            "properties": [
              {
                "id": "thresholds",
                "value": {
                  "mode": "absolute",
                  "steps": [
                    {
                      "color": "green",
                      "value": 0
                    },
                    {
                      "color": "orange",
                      "value": 1
                    },
                    {
                      "color": "red",
                      "value": 100
                    }
                  ]
                }
              },
              {
                "id": "custom.cellOptions",
                "value": {
                  "mode": "basic",
                  "type": "color-background"
                }
              }
            ]
          }
        ]
      },
      "gridPos": {
        "h": 11,
        "w": 12,
        "x": 0,
        "y": 24
      },
      "id": 14,
      "options": {
        "cellHeight": "sm",
        "showHeader": true,
        "sortBy": [
          {
            "desc": true,
            "displayName": "requests"
          }
        ]
      },
      "pluginVersion": "12.3.1",
      "targets": [
        {
          "editorType": "sql",
          "format": 1,
          "queryType": "table",
          "rawSql": "SELECT path, count() AS requests, round(avg(request_time) * 1000, 0) AS avg_ms, round(quantile(0.95)(request_time) * 1000, 0) AS p95_ms, countIf(status >= 400) AS errors FROM logs_nginx_${deployment_env}.access WHERE $__timeFilter(timestamp) AND host LIKE '$host' AND toString(status) LIKE '$status' AND method LIKE '$method' AND country_code LIKE '$country' GROUP BY path ORDER BY requests DESC LIMIT 20",
          "refId": "A"
        }
      ],
      "title": "Top Endpoints",
      "type": "table"
    },
    {
      "datasource": {
        "type": "grafana-clickhouse-datasource",
        "uid": "${DS_CLICKHOUSE}"
      },
      "fieldConfig": {
        "defaults": {
          "color": {
            "mode": "thresholds"
          },
          "custom": {
            "align": "auto",
            "cellOptions": {
              "type": "auto"
            },
            "footer": {
              "reducers": []
            },
            "inspect": false
          },
          "mappings": [],
          "thresholds": {
            "mode": "absolute",
            "steps": [
              {
                "color": "green",
                "value": 0
              }
            ]
          }
        },
        "overrides": [
          {
            "matcher": {
              "id": "byRegexp",
              "options": ".*_ms$"
            },
            "properties": [
              {
                "id": "unit",
                "value": "ms"
              },
              {
                "id": "thresholds",
                "value": {
                  "mode": "absolute",
                  "steps": [
                    {
                      "color": "green",
                      "value": 0
                    },
                    {
                      "color": "yellow",
                      "value": 500
                    },
                    {
                      "color": "orange",
                      "value": 1000
                    },
                    {
                      "color": "red",
                      "value": 2000
                    }
                  ]
                }
              },
              {
                "id": "custom.cellOptions",
                "value": {
                  "mode": "basic",
                  "type": "color-background"
                }
              }
            ]
          }
        ]
      },
      "gridPos": {
        "h": 11,
        "w": 12,
        "x": 12,
        "y": 24
      },
      "id": 15,
      "options": {
        "cellHeight": "sm",
        "showHeader": true,
        "sortBy": [
          {
            "desc": true,
            "displayName": "p95_ms"
          }
        ]
      },
      "pluginVersion": "12.3.1",
      "targets": [
        {
          "editorType": "sql",
          "format": 1,
          "queryType": "table",
          "rawSql": "SELECT path, count() AS requests, round(quantile(0.5)(request_time) * 1000, 0) AS p50_ms, round(quantile(0.95)(request_time) * 1000, 0) AS p95_ms, round(quantile(0.99)(request_time) * 1000, 0) AS p99_ms FROM logs_nginx_${deployment_env}.access WHERE $__timeFilter(timestamp) AND request_time > 0 AND host LIKE '$host' AND toString(status) LIKE '$status' AND method LIKE '$method' AND country_code LIKE '$country' GROUP BY path HAVING requests > 5 ORDER BY p95_ms DESC LIMIT 20",
          "refId": "A"
        }
      ],
      "title": "Slowest Endpoints (P95)",
      "type": "table"
    },
    {
      "collapsed": false,
      "gridPos": {
        "h": 1,
        "w": 24,
        "x": 0,
        "y": 35
      },
      "id": 104,
      "panels": [],
      "title": "Status & Errors",
      "type": "row"
    },
    {
      "datasource": {
        "type": "grafana-clickhouse-datasource",
        "uid": "${DS_CLICKHOUSE}"
      },
      "fieldConfig": {
        "defaults": {
          "color": {
            "mode": "palette-classic"
          },
          "custom": {
            "axisBorderShow": false,
            "axisCenteredZero": false,
            "axisColorMode": "text",
            "axisLabel": "",
            "axisPlacement": "auto",
            "barAlignment": 0,
            "barWidthFactor": 0.6,
            "drawStyle": "line",
            "fillOpacity": 10,
            "gradientMode": "opacity",
            "hideFrom": {
              "legend": false,
              "tooltip": false,
              "viz": false
            },
            "insertNulls": false,
            "lineInterpolation": "linear",
            "lineWidth": 1,
            "pointSize": 5,
            "scaleDistribution": {
              "type": "linear"
            },
            "showPoints": "never",
            "showValues": false,
            "spanNulls": false,
            "stacking": {
              "group": "A",
              "mode": "none"
            },
            "thresholdsStyle": {
              "mode": "off"
            }
          },
          "mappings": [],
          "thresholds": {
            "mode": "absolute",
            "steps": [
              {
                "color": "green",
                "value": 0
              }
            ]
          }
        },
        "overrides": [
          {
            "matcher": {
              "id": "byName",
              "options": "2xx OK"
            },
            "properties": [
              {
                "id": "color",
                "value": {
                  "fixedColor": "green",
                  "mode": "fixed"
                }
              }
            ]
          },
          {
            "matcher": {
              "id": "byName",
              "options": "3xx Redirect"
            },
            "properties": [
              {
                "id": "color",
                "value": {
                  "fixedColor": "blue",
                  "mode": "fixed"
                }
              }
            ]
          },
          {
            "matcher": {
              "id": "byName",
              "options": "4xx Client Error"
            },
            "properties": [
              {
                "id": "color",
                "value": {
                  "fixedColor": "orange",
                  "mode": "fixed"
                }
              }
            ]
          },
          {
            "matcher": {
              "id": "byName",
              "options": "5xx Server Error"
            },
            "properties": [
              {
                "id": "color",
                "value": {
                  "fixedColor": "red",
                  "mode": "fixed"
                }
              }
            ]
          },
          {
            "matcher": {
              "id": "byName",
              "options": "Blocked"
            },
            "properties": [
              {
                "id": "color",
                "value": {
                  "fixedColor": "purple",
                  "mode": "fixed"
                }
              }
            ]
          }
        ]
      },
      "gridPos": {
        "h": 10,
        "w": 14,
        "x": 0,
        "y": 36
      },
      "id": 16,
      "options": {
        "legend": {
          "calcs": [
            "sum"
          ],
          "displayMode": "list",
          "placement": "bottom",
          "showLegend": true
        },
        "tooltip": {
          "hideZeros": true,
          "mode": "multi",
          "sort": "desc"
        }
      },
      "pluginVersion": "12.3.0",
      "targets": [
        {
          "editorType": "sql",
          "format": 1,
          "queryType": "table",
          "rawSql": "SELECT $__timeInterval(timestamp) AS time, multiIf(status < 300, '2xx OK', status < 400, '3xx Redirect', status < 500, '4xx Client Error', status = 444, 'Blocked', '5xx Server Error') AS status_class, count() AS requests FROM logs_nginx_${deployment_env}.access WHERE $__timeFilter(timestamp) AND host LIKE '$host' AND toString(status) LIKE '$status' AND method LIKE '$method' AND country_code LIKE '$country' GROUP BY time, status_class ORDER BY time",
          "refId": "A"
        }
      ],
      "title": "Status Codes Over Time",
      "type": "timeseries"
    },
    {
      "datasource": {
        "type": "grafana-clickhouse-datasource",
        "uid": "${DS_CLICKHOUSE}"
      },
      "fieldConfig": {
        "defaults": {
          "color": {
            "mode": "thresholds"
          },
          "custom": {
            "align": "left",
            "cellOptions": {
              "type": "auto"
            },
            "footer": {
              "reducers": []
            },
            "inspect": false,
            "wrapText": false
          },
          "mappings": [],
          "thresholds": {
            "mode": "absolute",
            "steps": [
              {
                "color": "green",
                "value": 0
              },
              {
                "color": "red",
                "value": 400
              }
            ]
          },
          "unit": "short"
        },
        "overrides": [
          {
            "matcher": {
              "id": "byName",
              "options": "count"
            },
            "properties": [
              {
                "id": "custom.cellOptions",
                "value": {
                  "mode": "gradient",
                  "type": "gauge",
                  "valueDisplayMode": "text"
                }
              },
              {
                "id": "custom.width",
                "value": 466
              }
            ]
          },
          {
            "matcher": {
              "id": "byName",
              "options": "status"
            },
            "properties": [
              {
                "id": "thresholds",
                "value": {
                  "mode": "absolute",
                  "steps": [
                    {
                      "color": "green",
                      "value": 0
                    },
                    {
                      "color": "orange",
                      "value": 400
                    },
                    {
                      "color": "red",
                      "value": 500
                    }
                  ]
                }
              },
              {
                "id": "custom.cellOptions",
                "value": {
                  "mode": "basic",
                  "type": "color-text"
                }
              },
              {
                "id": "custom.width",
                "value": 54
              }
            ]
          },
          {
            "matcher": {
              "id": "byName",
              "options": "pct"
            },
            "properties": [
              {
                "id": "custom.width",
                "value": 61
              }
            ]
          }
        ]
      },
      "gridPos": {
        "h": 10,
        "w": 10,
        "x": 14,
        "y": 36
      },
      "id": 17,
      "options": {
        "cellHeight": "md",
        "enablePagination": false,
        "frozenColumns": {
          "left": 1
        },
        "showHeader": true,
        "sortBy": [
          {
            "desc": true,
            "displayName": "count"
          }
        ]
      },
      "pluginVersion": "12.3.0",
      "targets": [
        {
          "editorType": "sql",
          "format": 1,
          "meta": {},
          "pluginVersion": "4.11.4",
          "queryType": "table",
          "rawSql": "SELECT status, count() AS count, round(count() * 100.0 / sum(count()) OVER (), 2) AS pct, any(path) AS example_path FROM logs_nginx_${deployment_env}.access WHERE $__timeFilter(timestamp) AND status >= 400 AND status != 444 AND host LIKE '$host' AND toString(status) LIKE '$status' AND method LIKE '$method' AND country_code LIKE '$country' GROUP BY status ORDER BY count DESC LIMIT 15",
          "refId": "A"
        }
      ],
      "title": "Error Codes Breakdown",
      "type": "table"
    },
    {
      "collapsed": false,
      "gridPos": {
        "h": 1,
        "w": 24,
        "x": 0,
        "y": 46
      },
      "id": 105,
      "panels": [],
      "title": "Geographic & Traffic Sources",
      "type": "row"
    },
    {
      "datasource": {
        "type": "grafana-clickhouse-datasource",
        "uid": "${DS_CLICKHOUSE}"
      },
      "fieldConfig": {
        "defaults": {
          "color": {
            "mode": "thresholds"
          },
          "custom": {
            "hideFrom": {
              "legend": false,
              "tooltip": false,
              "viz": false
            }
          },
          "fieldMinMax": false,
          "mappings": [],
          "thresholds": {
            "mode": "percentage",
            "steps": [
              {
                "color": "green",
                "value": 0
              },
              {
                "color": "super-light-green",
                "value": 0
              },
              {
                "color": "light-green",
                "value": 5
              },
              {
                "color": "green",
                "value": 10
              },
              {
                "color": "semi-dark-green",
                "value": 20
              },
              {
                "color": "dark-green",
                "value": 50
              }
            ]
          }
        },
        "overrides": []
      },
      "gridPos": {
        "h": 12,
        "w": 15,
        "x": 0,
        "y": 47
      },
      "id": 18,
      "options": {
        "basemap": {
          "config": {},
          "name": "Layer 0",
          "noRepeat": true,
          "type": "default"
        },
        "controls": {
          "mouseWheelZoom": false,
          "showAttribution": false,
          "showDebug": false,
          "showMeasure": false,
          "showScale": false,
          "showZoom": false
        },
        "layers": [
          {
            "config": {
              "showLegend": true,
              "style": {
                "color": {
                  "field": "requests",
                  "fixed": "dark-green"
                },
                "opacity": 0.9,
                "rotation": {
                  "fixed": 0,
                  "max": 360,
                  "min": -360,
                  "mode": "mod"
                },
                "size": {
                  "field": "requests",
                  "fixed": 5,
                  "max": 30,
                  "min": 5
                },
                "symbol": {
                  "fixed": "img/icons/marker/circle.svg",
                  "mode": "fixed"
                },
                "symbolAlign": {
                  "horizontal": "center",
                  "vertical": "center"
                },
                "text": {
                  "fixed": "",
                  "mode": "fixed"
                }
              }
            },
            "layer-tooltip": false,
            "location": {
              "gazetteer": "public/build/gazetteer/countries.json",
              "lookup": "country_code",
              "mode": "lookup"
            },
            "name": "Requests",
            "tooltip": true,
            "type": "markers"
          }
        ],
        "tooltip": {
          "mode": "details"
        },
        "view": {
          "allLayers": true,
          "id": "zero",
          "lat": 20,
          "lon": 0,
          "noRepeat": true,
          "zoom": 1.5
        }
      },
      "pluginVersion": "12.3.0",
      "targets": [
        {
          "editorType": "sql",
          "format": 1,
          "queryType": "table",
          "rawSql": "SELECT country_code, count() AS requests FROM logs_nginx_${deployment_env}.access WHERE $__timeFilter(timestamp) AND country_code != '' AND host LIKE '$host' AND toString(status) LIKE '$status' AND method LIKE '$method' AND country_code LIKE '$country' GROUP BY country_code ORDER BY requests DESC",
          "refId": "A"
        }
      ],
      "title": "Traffic by Country",
      "type": "geomap"
    },
    {
      "datasource": {
        "type": "grafana-clickhouse-datasource",
        "uid": "${DS_CLICKHOUSE}"
      },
      "fieldConfig": {
        "defaults": {
          "color": {
            "mode": "continuous-GrYlRd"
          },
          "custom": {
            "axisBorderShow": false,
            "axisCenteredZero": false,
            "axisColorMode": "text",
            "axisLabel": "",
            "axisPlacement": "auto",
            "barAlignment": 0,
            "barWidthFactor": 0.6,
            "drawStyle": "line",
            "fillOpacity": 20,
            "gradientMode": "scheme",
            "hideFrom": {
              "legend": false,
              "tooltip": false,
              "viz": false
            },
            "insertNulls": false,
            "lineInterpolation": "smooth",
            "lineWidth": 3,
            "pointSize": 5,
            "scaleDistribution": {
              "type": "linear"
            },
            "showPoints": "auto",
            "showValues": false,
            "spanNulls": false,
            "stacking": {
              "group": "A",
              "mode": "none"
            },
            "thresholdsStyle": {
              "mode": "off"
            }
          },
          "mappings": [],
          "thresholds": {
            "mode": "absolute",
            "steps": [
              {
                "color": "green",
                "value": 0
              },
              {
                "color": "red",
                "value": 80
              }
            ]
          }
        },
        "overrides": [
          {
            "matcher": {
              "id": "byName",
              "options": "Via CDN"
            },
            "properties": [
              {
                "id": "color",
                "value": {
                  "fixedColor": "green",
                  "mode": "fixed"
                }
              }
            ]
          },
          {
            "matcher": {
              "id": "byName",
              "options": "Direct"
            },
            "properties": [
              {
                "id": "color",
                "value": {
                  "fixedColor": "orange",
                  "mode": "fixed"
                }
              }
            ]
          },
          {
            "matcher": {
              "id": "byName",
              "options": "Blocked"
            },
            "properties": [
              {
                "id": "color",
                "value": {
                  "fixedColor": "purple",
                  "mode": "fixed"
                }
              }
            ]
          }
        ]
      },
      "gridPos": {
        "h": 12,
        "w": 9,
        "x": 15,
        "y": 47
      },
      "id": 20,
      "options": {
        "legend": {
          "calcs": [],
          "displayMode": "hidden",
          "placement": "right",
          "showLegend": false
        },
        "tooltip": {
          "hideZeros": false,
          "mode": "single",
          "sort": "none"
        }
      },
      "pluginVersion": "12.3.0",
      "targets": [
        {
          "editorType": "sql",
          "format": 1,
          "queryType": "table",
          "rawSql": "SELECT $__timeInterval(timestamp) AS time, multiIf(cf_ray != '', 'Via CDN', status = 444, 'Blocked', 'Direct') AS traffic_type, count() AS requests FROM logs_nginx_${deployment_env}.access WHERE $__timeFilter(timestamp) AND host LIKE '$host' AND toString(status) LIKE '$status' AND method LIKE '$method' AND country_code LIKE '$country' GROUP BY time, traffic_type ORDER BY time",
          "refId": "A"
        }
      ],
      "title": "Traffic Source",
      "type": "timeseries"
    },
    {
      "datasource": {
        "type": "grafana-clickhouse-datasource",
        "uid": "${DS_CLICKHOUSE}"
      },
      "fieldConfig": {
        "defaults": {
          "color": {
            "mode": "continuous-YlRd"
          },
          "custom": {
            "axisBorderShow": false,
            "axisCenteredZero": false,
            "axisColorMode": "text",
            "axisLabel": "",
            "axisPlacement": "auto",
            "fillOpacity": 80,
            "gradientMode": "hue",
            "hideFrom": {
              "legend": false,
              "tooltip": false,
              "viz": false
            },
            "lineWidth": 1,
            "scaleDistribution": {
              "log": 2,
              "type": "log"
            },
            "thresholdsStyle": {
              "mode": "off"
            }
          },
          "mappings": [],
          "thresholds": {
            "mode": "absolute",
            "steps": [
              {
                "color": "green",
                "value": 0
              }
            ]
          },
          "unit": "short"
        },
        "overrides": []
      },
      "gridPos": {
        "h": 12,
        "w": 24,
        "x": 0,
        "y": 59
      },
      "id": 19,
      "options": {
        "barRadius": 0,
        "barWidth": 0.95,
        "fullHighlight": false,
        "groupWidth": 0.7,
        "legend": {
          "calcs": [],
          "displayMode": "list",
          "placement": "right",
          "showLegend": true
        },
        "orientation": "horizontal",
        "showValue": "auto",
        "stacking": "none",
        "tooltip": {
          "hideZeros": false,
          "mode": "single",
          "sort": "none"
        },
        "xTickLabelRotation": 0,
        "xTickLabelSpacing": 0
      },
      "pluginVersion": "12.3.0",
      "targets": [
        {
          "editorType": "sql",
          "format": 1,
          "meta": {},
          "pluginVersion": "4.11.4",
          "queryType": "table",
          "rawSql": "SELECT country_code, count() AS requests FROM logs_nginx_${deployment_env}.access WHERE $__timeFilter(timestamp) AND country_code != '' AND host LIKE '$host' AND toString(status) LIKE '$status' AND method LIKE '$method' AND country_code LIKE '$country' GROUP BY country_code ORDER BY requests DESC LIMIT 10",
          "refId": "A"
        }
      ],
      "title": "Top Countries",
      "type": "barchart"
    },
    {
      "collapsed": false,
      "gridPos": {
        "h": 1,
        "w": 24,
        "x": 0,
        "y": 71
      },
      "id": 106,
      "panels": [],
      "title": "Infrastructure",
      "type": "row"
    },
    {
      "datasource": {
        "type": "grafana-clickhouse-datasource",
        "uid": "${DS_CLICKHOUSE}"
      },
      "fieldConfig": {
        "defaults": {
          "custom": {
            "align": "auto",
            "cellOptions": {
              "type": "auto"
            },
            "footer": {
              "reducers": []
            },
            "inspect": false
          },
          "mappings": [],
          "thresholds": {
            "mode": "absolute",
            "steps": [
              {
                "color": "green",
                "value": 0
              },
              {
                "color": "red",
                "value": 80
              }
            ]
          }
        },
        "overrides": [
          {
            "matcher": {
              "id": "byName",
              "options": "requests"
            },
            "properties": [
              {
                "id": "custom.cellOptions",
                "value": {
                  "mode": "gradient",
                  "type": "gauge",
                  "valueDisplayMode": "text"
                }
              }
            ]
          },
          {
            "matcher": {
              "id": "byName",
              "options": "error_pct"
            },
            "properties": [
              {
                "id": "unit",
                "value": "percent"
              },
              {
                "id": "thresholds",
                "value": {
                  "mode": "absolute",
                  "steps": [
                    {
                      "color": "green",
                      "value": 0
                    },
                    {
                      "color": "yellow",
                      "value": 1
                    },
                    {
                      "color": "red",
                      "value": 5
                    }
                  ]
                }
              },
              {
                "id": "custom.cellOptions",
                "value": {
                  "mode": "basic",
                  "type": "color-background"
                }
              }
            ]
          },
          {
            "matcher": {
              "id": "byName",
              "options": "p95_ms"
            },
            "properties": [
              {
                "id": "unit",
                "value": "ms"
              },
              {
                "id": "thresholds",
                "value": {
                  "mode": "absolute",
                  "steps": [
                    {
                      "color": "green",
                      "value": 0
                    },
                    {
                      "color": "yellow",
                      "value": 500
                    },
                    {
                      "color": "red",
                      "value": 1000
                    }
                  ]
                }
              },
              {
                "id": "custom.cellOptions",
                "value": {
                  "mode": "basic",
                  "type": "color-background"
                }
              }
            ]
          }
        ]
      },
      "gridPos": {
        "h": 7,
        "w": 6,
        "x": 0,
        "y": 72
      },
      "id": 21,
      "options": {
        "cellHeight": "lg",
        "showHeader": true
      },
      "pluginVersion": "12.3.0",
      "targets": [
        {
          "editorType": "sql",
          "format": 1,
          "queryType": "table",
          "rawSql": "SELECT source_host, count() AS requests, round(countIf(status >= 500) * 100.0 / count(), 2) AS error_pct, round(quantile(0.95)(request_time) * 1000, 0) AS p95_ms FROM logs_nginx_${deployment_env}.access WHERE $__timeFilter(timestamp) AND host LIKE '$host' AND toString(status) LIKE '$status' AND method LIKE '$method' AND country_code LIKE '$country' GROUP BY source_host ORDER BY requests DESC",
          "refId": "A"
        }
      ],
      "title": "Server Health (Source Host)",
      "type": "table"
    },
    {
      "datasource": {
        "type": "grafana-clickhouse-datasource",
        "uid": "${DS_CLICKHOUSE}"
      },
      "fieldConfig": {
        "defaults": {
          "color": {
            "mode": "thresholds"
          },
          "mappings": [
            {
              "options": {
                "BYPASS": {
                  "color": "orange",
                  "index": 2
                },
                "EXPIRED": {
                  "color": "blue",
                  "index": 3
                },
                "HIT": {
                  "color": "green",
                  "index": 0
                },
                "MISS": {
                  "color": "yellow",
                  "index": 1
                },
                "No Cache": {
                  "color": "gray",
                  "index": 4
                }
              },
              "type": "value"
            }
          ],
          "thresholds": {
            "mode": "absolute",
            "steps": [
              {
                "color": "blue",
                "value": 0
              }
            ]
          },
          "unit": "short"
        },
        "overrides": []
      },
      "gridPos": {
        "h": 7,
        "w": 6,
        "x": 6,
        "y": 72
      },
      "id": 23,
      "options": {
        "displayMode": "gradient",
        "legend": {
          "calcs": [],
          "displayMode": "list",
          "placement": "bottom",
          "showLegend": false
        },
        "maxVizHeight": 300,
        "minVizHeight": 16,
        "minVizWidth": 8,
        "namePlacement": "auto",
        "orientation": "horizontal",
        "reduceOptions": {
          "calcs": [
            "lastNotNull"
          ],
          "fields": "",
          "values": false
        },
        "showUnfilled": true,
        "sizing": "auto",
        "valueMode": "color"
      },
      "pluginVersion": "12.3.0",
      "targets": [
        {
          "editorType": "sql",
          "format": 1,
          "queryType": "table",
          "rawSql": "SELECT if(upstream_cache_status = '', 'No Cache', upstream_cache_status) AS cache_status, count() AS requests FROM logs_nginx_${deployment_env}.access WHERE $__timeFilter(timestamp) AND host LIKE '$host' AND toString(status) LIKE '$status' AND method LIKE '$method' AND country_code LIKE '$country' GROUP BY cache_status ORDER BY requests DESC",
          "refId": "A"
        }
      ],
      "title": "Cache Status",
      "type": "bargauge"
    },
    {
      "datasource": {
        "type": "grafana-clickhouse-datasource",
        "uid": "${DS_CLICKHOUSE}"
      },
      "fieldConfig": {
        "defaults": {
          "color": {
            "mode": "palette-classic"
          },
          "custom": {
            "hideFrom": {
              "legend": false,
              "tooltip": false,
              "viz": false
            }
          },
          "mappings": [
            {
              "options": {
                "No SSL": {
                  "color": "dark-red",
                  "index": 4
                },
                "TLSv1": {
                  "color": "red",
                  "index": 3
                },
                "TLSv1.1": {
                  "color": "orange",
                  "index": 2
                },
                "TLSv1.2": {
                  "color": "blue",
                  "index": 1
                },
                "TLSv1.3": {
                  "color": "green",
                  "index": 0
                }
              },
              "type": "value"
            }
          ],
          "unit": "short"
        },
        "overrides": []
      },
      "gridPos": {
        "h": 7,
        "w": 6,
        "x": 12,
        "y": 72
      },
      "id": 301,
      "options": {
        "displayLabels": [
          "percent"
        ],
        "legend": {
          "calcs": [],
          "displayMode": "list",
          "placement": "right",
          "showLegend": true,
          "values": [
            "percent",
            "value"
          ]
        },
        "pieType": "pie",
        "reduceOptions": {
          "calcs": [
            "lastNotNull"
          ],
          "fields": "",
          "values": true
        },
        "sort": "desc",
        "tooltip": {
          "hideZeros": false,
          "mode": "single",
          "sort": "none"
        }
      },
      "pluginVersion": "12.3.0",
      "targets": [
        {
          "editorType": "sql",
          "format": 1,
          "queryType": "table",
          "rawSql": "SELECT if(ssl_protocol = '', 'No SSL', ssl_protocol) AS protocol, count() AS requests FROM logs_nginx_${deployment_env}.access WHERE $__timeFilter(timestamp) AND host LIKE '$host' AND toString(status) LIKE '$status' AND method LIKE '$method' AND country_code LIKE '$country' GROUP BY protocol ORDER BY requests DESC",
          "refId": "A"
        }
      ],
      "title": "SSL/TLS Versions",
      "type": "piechart"
    },
    {
      "datasource": {
        "type": "grafana-clickhouse-datasource",
        "uid": "${DS_CLICKHOUSE}"
      },
      "fieldConfig": {
        "defaults": {
          "color": {
            "mode": "palette-classic"
          },
          "custom": {
            "hideFrom": {
              "legend": false,
              "tooltip": false,
              "viz": false
            }
          },
          "mappings": [],
          "unit": "short"
        },
        "overrides": []
      },
      "gridPos": {
        "h": 7,
        "w": 6,
        "x": 18,
        "y": 72
      },
      "id": 22,
      "options": {
        "displayLabels": [
          "percent"
        ],
        "legend": {
          "calcs": [],
          "displayMode": "list",
          "placement": "right",
          "showLegend": true,
          "values": [
            "percent",
            "value"
          ]
        },
        "pieType": "pie",
        "reduceOptions": {
          "calcs": [
            "lastNotNull"
          ],
          "fields": "",
          "values": true
        },
        "sort": "desc",
        "tooltip": {
          "hideZeros": false,
          "mode": "single",
          "sort": "none"
        }
      },
      "pluginVersion": "12.3.0",
      "targets": [
        {
          "editorType": "sql",
          "format": 1,
          "queryType": "table",
          "rawSql": "SELECT method, count() AS requests FROM logs_nginx_${deployment_env}.access WHERE $__timeFilter(timestamp) AND host LIKE '$host' AND toString(status) LIKE '$status' AND method LIKE '$method' AND country_code LIKE '$country' GROUP BY method ORDER BY requests DESC LIMIT 10",
          "refId": "A"
        }
      ],
      "title": "HTTP Methods",
      "type": "piechart"
    },
    {
      "collapsed": false,
      "gridPos": {
        "h": 1,
        "w": 24,
        "x": 0,
        "y": 79
      },
      "id": 107,
      "panels": [],
      "title": "Debug",
      "type": "row"
    },
    {
      "datasource": {
        "type": "grafana-clickhouse-datasource",
        "uid": "${DS_CLICKHOUSE}"
      },
      "fieldConfig": {
        "defaults": {
          "color": {
            "mode": "thresholds"
          },
          "custom": {
            "align": "auto",
            "cellOptions": {
              "type": "auto"
            },
            "footer": {
              "reducers": []
            },
            "inspect": false
          },
          "mappings": [],
          "thresholds": {
            "mode": "absolute",
            "steps": [
              {
                "color": "green",
                "value": 0
              }
            ]
          }
        },
        "overrides": [
          {
            "matcher": {
              "id": "byName",
              "options": "total_ms"
            },
            "properties": [
              {
                "id": "unit",
                "value": "ms"
              },
              {
                "id": "thresholds",
                "value": {
                  "mode": "absolute",
                  "steps": [
                    {
                      "color": "yellow",
                      "value": 0
                    },
                    {
                      "color": "orange",
                      "value": 2000
                    },
                    {
                      "color": "red",
                      "value": 5000
                    }
                  ]
                }
              },
              {
                "id": "custom.cellOptions",
                "value": {
                  "mode": "basic",
                  "type": "color-background"
                }
              }
            ]
          },
          {
            "matcher": {
              "id": "byName",
              "options": "upstream_ms"
            },
            "properties": [
              {
                "id": "unit",
                "value": "ms"
              }
            ]
          },
          {
            "matcher": {
              "id": "byName",
              "options": "status"
            },
            "properties": [
              {
                "id": "thresholds",
                "value": {
                  "mode": "absolute",
                  "steps": [
                    {
                      "color": "green",
                      "value": 0
                    },
                    {
                      "color": "orange",
                      "value": 400
                    },
                    {
                      "color": "red",
                      "value": 500
                    }
                  ]
                }
              },
              {
                "id": "custom.cellOptions",
                "value": {
                  "mode": "basic",
                  "type": "color-text"
                }
              }
            ]
          }
        ]
      },
      "gridPos": {
        "h": 10,
        "w": 24,
        "x": 0,
        "y": 80
      },
      "id": 24,
      "options": {
        "cellHeight": "sm",
        "showHeader": true,
        "sortBy": [
          {
            "desc": true,
            "displayName": "total_ms"
          }
        ]
      },
      "pluginVersion": "12.3.0",
      "targets": [
        {
          "editorType": "sql",
          "format": 1,
          "queryType": "table",
          "rawSql": "SELECT timestamp, host, path, round(request_time * 1000, 0) AS total_ms, round(upstream_response_time * 1000, 0) AS upstream_ms, status, remote_addr FROM logs_nginx_${deployment_env}.access WHERE $__timeFilter(timestamp) AND request_time > 2 AND host LIKE '$host' AND toString(status) LIKE '$status' AND method LIKE '$method' AND country_code LIKE '$country' ORDER BY request_time DESC LIMIT 50",
          "refId": "A"
        }
      ],
      "title": "Slow Requests (>2s)",
      "type": "table"
    },
    {
      "collapsed": false,
      "gridPos": {
        "h": 1,
        "w": 24,
        "x": 0,
        "y": 90
      },
      "id": 200,
      "panels": [],
      "title": "Client & Security Analysis",
      "type": "row"
    },
    {
      "datasource": {
        "type": "grafana-clickhouse-datasource",
        "uid": "${DS_CLICKHOUSE}"
      },
      "fieldConfig": {
        "defaults": {
          "color": {
            "mode": "thresholds"
          },
          "custom": {
            "align": "auto",
            "cellOptions": {
              "type": "auto"
            },
            "footer": {
              "reducers": []
            },
            "inspect": false
          },
          "mappings": [],
          "thresholds": {
            "mode": "absolute",
            "steps": [
              {
                "color": "green",
                "value": 0
              }
            ]
          }
        },
        "overrides": [
          {
            "matcher": {
              "id": "byName",
              "options": "requests"
            },
            "properties": [
              {
                "id": "custom.cellOptions",
                "value": {
                  "mode": "gradient",
                  "type": "gauge",
                  "valueDisplayMode": "text"
                }
              }
            ]
          }
        ]
      },
      "gridPos": {
        "h": 8,
        "w": 12,
        "x": 0,
        "y": 91
      },
      "id": 201,
      "options": {
        "cellHeight": "sm",
        "showHeader": true,
        "sortBy": [
          {
            "desc": true,
            "displayName": "requests"
          }
        ]
      },
      "pluginVersion": "12.3.0",
      "targets": [
        {
          "editorType": "sql",
          "format": 1,
          "queryType": "table",
          "rawSql": "SELECT user_agent, count() AS requests FROM logs_nginx_${deployment_env}.access WHERE $__timeFilter(timestamp) AND host LIKE '$host' AND toString(status) LIKE '$status' AND method LIKE '$method' AND country_code LIKE '$country' GROUP BY user_agent ORDER BY requests DESC LIMIT 20",
          "refId": "A"
        }
      ],
      "title": "Top User Agents",
      "type": "table"
    },
    {
      "datasource": {
        "type": "grafana-clickhouse-datasource",
        "uid": "${DS_CLICKHOUSE}"
      },
      "fieldConfig": {
        "defaults": {
          "color": {
            "mode": "thresholds"
          },
          "custom": {
            "align": "auto",
            "cellOptions": {
              "type": "auto"
            },
            "footer": {
              "reducers": []
            },
            "inspect": false
          },
          "mappings": [],
          "thresholds": {
            "mode": "absolute",
            "steps": [
              {
                "color": "green",
                "value": 0
              }
            ]
          }
        },
        "overrides": []
      },
      "gridPos": {
        "h": 8,
        "w": 12,
        "x": 12,
        "y": 91
      },
      "id": 202,
      "options": {
        "cellHeight": "sm",
        "showHeader": true,
        "sortBy": [
          {
            "desc": true,
            "displayName": "requests"
          }
        ]
      },
      "pluginVersion": "12.3.0",
      "targets": [
        {
          "editorType": "sql",
          "format": 1,
          "queryType": "table",
          "rawSql": "SELECT referer, count() AS requests FROM logs_nginx_${deployment_env}.access WHERE $__timeFilter(timestamp) AND host LIKE '$host' AND toString(status) LIKE '$status' AND method LIKE '$method' AND country_code LIKE '$country' AND referer != '' GROUP BY referer ORDER BY requests DESC LIMIT 20",
          "refId": "A"
        }
      ],
      "title": "Top Referrers",
      "type": "table"
    }
  ],
  "preload": false,
  "refresh": "",
  "schemaVersion": 42,
  "tags": [
    "nginx",
    "logs",
    "clickhouse"
  ],
  "templating": {
    "list": [
      {
        "current": {
          "text": "prd",
          "value": "prd"
        },
        "label": "Environment",
        "name": "deployment_env",
        "options": [
          {
            "selected": false,
            "text": "stg",
            "value": "stg"
          },
          {
            "selected": true,
            "text": "prd",
            "value": "prd"
          }
        ],
        "query": "stg,prd",
        "type": "custom"
      },
      {
        "allValue": "%",
        "current": {
          "text": "All",
          "value": "$__all"
        },
        "datasource": {
          "type": "grafana-clickhouse-datasource",
          "uid": "${DS_CLICKHOUSE}"
        },
        "definition": "SELECT DISTINCT host FROM logs_nginx_${deployment_env}.access WHERE timestamp > now() - INTERVAL 1 DAY ORDER BY host",
        "includeAll": true,
        "label": "Host",
        "name": "host",
        "options": [],
        "query": "SELECT DISTINCT host FROM logs_nginx_${deployment_env}.access WHERE timestamp > now() - INTERVAL 1 DAY ORDER BY host",
        "refresh": 2,
        "type": "query"
      },
      {
        "current": {
          "text": "clickhouse-logs",
          "value": "af84wpojvuxhcb"
        },
        "label": "Data Source",
        "name": "DS_CLICKHOUSE",
        "options": [],
        "query": "grafana-clickhouse-datasource",
        "refresh": 1,
        "type": "datasource"
      },
      {
        "allValue": "%",
        "current": {
          "text": "All",
          "value": "$__all"
        },
        "datasource": {
          "type": "grafana-clickhouse-datasource",
          "uid": "${DS_CLICKHOUSE}"
        },
        "definition": "SELECT DISTINCT method FROM logs_nginx_${deployment_env}.access ORDER BY method",
        "includeAll": true,
        "label": "Method",
        "name": "method",
        "options": [],
        "query": "SELECT DISTINCT method FROM logs_nginx_${deployment_env}.access ORDER BY method",
        "refresh": 2,
        "type": "query"
      },
      {
        "allValue": "%",
        "current": {
          "text": "All",
          "value": "$__all"
        },
        "datasource": {
          "type": "grafana-clickhouse-datasource",
          "uid": "${DS_CLICKHOUSE}"
        },
        "definition": "SELECT DISTINCT toString(status) FROM logs_nginx_${deployment_env}.access ORDER BY status",
        "includeAll": true,
        "label": "Status",
        "name": "status",
        "options": [],
        "query": "SELECT DISTINCT toString(status) FROM logs_nginx_${deployment_env}.access ORDER BY status",
        "refresh": 2,
        "type": "query"
      },
      {
        "allValue": "%",
        "current": {
          "text": "All",
          "value": "$__all"
        },
        "datasource": {
          "type": "grafana-clickhouse-datasource",
          "uid": "${DS_CLICKHOUSE}"
        },
        "definition": "SELECT DISTINCT country_code FROM logs_nginx_${deployment_env}.access WHERE country_code != '' ORDER BY country_code",
        "includeAll": true,
        "label": "Country",
        "name": "country",
        "options": [],
        "query": "SELECT DISTINCT country_code FROM logs_nginx_${deployment_env}.access WHERE country_code != '' ORDER BY country_code",
        "refresh": 2,
        "type": "query"
      }
    ]
  },
  "time": {
    "from": "now-5m",
    "to": "now"
  },
  "timepicker": {},
  "timezone": "browser",
  "title": "NGINX Access Logs",
  "uid": "nginx-access-logs",
  "version": 17
}
